oneenv/__init__.py
oneenv/cli.py
oneenv/core.py
oneenv/info_api.py
oneenv/models.py
oneenv-0.4.0.dist-info/licenses/LICENSE
oneenv-0.4.0.dist-info/METADATA
oneenv-0.4.0.dist-info/WHEEL
oneenv-0.4.0.dist-info/entry_points.txt
oneenv-0.4.0.dist-info/top_level.txt
oneenv-0.4.0.dist-info/RECORD
