Metadata-Version: 2.4
Name: oneenv
Version: 0.4.0
Summary: OneEnv: Environment variable management and generation tool
Requires-Python: >=3.10
License-File: LICENSE
Requires-Dist: python-dotenv>=1.0.1
Requires-Dist: pydantic>=2.0.0
Requires-Dist: typing-extensions>=4.0.0; python_version < "3.10"
Provides-Extra: dev
Requires-Dist: pytest>=8.3.4; extra == "dev"
Dynamic: license-file
